llm_client/__init__.py
llm_client/base_llm_client.py
llm_client/consts.py
llm_client/llm_api_client/__init__.py
llm_client/llm_api_client/ai21_client.py
llm_client/llm_api_client/aleph_alpha_client.py
llm_client/llm_api_client/anthropic_client.py
llm_client/llm_api_client/base_llm_api_client.py
llm_client/llm_api_client/google_client.py
llm_client/llm_api_client/huggingface_client.py
llm_client/llm_api_client/llm_api_client_factory.py
llm_client/llm_api_client/openai_client.py
llm_client/llm_client/__init__.py
llm_client/llm_client/local_client.py
llm_client/sync/__init__.py
llm_client/sync/sync_llm_api_client_factory.py
llm_client-0.7.0.dist-info/METADATA
llm_client-0.7.0.dist-info/WHEEL
llm_client-0.7.0.dist-info/licenses/LICENSE
llm_client-0.7.0.dist-info/RECORD
