Metadata-Version: 2.1
Name: llm-client
Version: 0.7.0
Summary: SDK for using LLM
Project-URL: Homepage, https://github.com/uripeled2/llm-client-sdk
Author-email: Uri Peled <uripeled2@gmail.com>
License-Expression: MIT
License-File: LICENSE
Classifier: Intended Audience :: Developers
Classifier: License :: OSI Approved :: MIT License
Classifier: Operating System :: OS Independent
Classifier: Programming Language :: Python :: 3 :: Only
Classifier: Programming Language :: Python :: 3.9
Classifier: Programming Language :: Python :: 3.10
Classifier: Programming Language :: Python :: 3.11
Requires-Python: >=3.9
Requires-Dist: aiohttp<4.0.0,>=3.0.0
Provides-Extra: all
Requires-Dist: llm-client[api,local,sync]; extra == 'all'
Provides-Extra: anthropic
Requires-Dist: anthropic>=0.3.2; extra == 'anthropic'
Provides-Extra: api
Requires-Dist: llm-client[anthropic,google,huggingface,openai]; extra == 'api'
Provides-Extra: google
Requires-Dist: google-generativeai>=0.1.0; extra == 'google'
Provides-Extra: huggingface
Requires-Dist: transformers>=4.0.0; extra == 'huggingface'
Provides-Extra: local
Requires-Dist: transformers>=4.0.0; extra == 'local'
Provides-Extra: openai
Requires-Dist: dataclasses-json>=0.5.0; extra == 'openai'
Requires-Dist: openai>=0.27.4; extra == 'openai'
Requires-Dist: tiktoken>=0.3.3; extra == 'openai'
Provides-Extra: sync
Requires-Dist: async-to-sync>=0.2.0; extra == 'sync'
Provides-Extra: test
Requires-Dist: aioresponses; extra == 'test'
Requires-Dist: pytest; extra == 'test'
Requires-Dist: pytest-aiohttp; extra == 'test'
Requires-Dist: pytest-asyncio; extra == 'test'
Requires-Dist: pytest-mock; extra == 'test'
